nbrmd/__init__.py
nbrmd/cell_metadata.py
nbrmd/cells.py
nbrmd/cli.py
nbrmd/combine.py
nbrmd/contentsmanager.py
nbrmd/header.py
nbrmd/languages.py
nbrmd/nbrmd.py
nbrmd/rmarkdownexporter.py
nbrmd-0.4.2.dist-info/METADATA
nbrmd-0.4.2.dist-info/RECORD
nbrmd-0.4.2.dist-info/WHEEL
nbrmd-0.4.2.dist-info/entry_points.txt
nbrmd-0.4.2.dist-info/top_level.txt
tests/__init__.py
tests/python_notebook_sample.py
tests/test_active_cells.py
tests/test_cell_metadata.py
tests/test_cells.py
tests/test_cli.py
tests/test_combine.py
tests/test_contentsmanager.py
tests/test_header.py
tests/test_ipynb_to_R.py
tests/test_ipynb_to_py.py
tests/test_ipynb_to_rmd.py
tests/test_nbconvert.py
tests/test_nbrmd_errors.py
tests/test_open_readme.py
tests/test_read_all_py.py
tests/test_read_incomplete_rmd.py
tests/test_read_simple_R.py
tests/test_read_simple_python.py
tests/test_read_simple_rmd.py
tests/test_rmd_to_ipynb.py
tests/test_save_multiple.py
tests/test_unicode.py
tests/utils.py
